cfs/__init__.py
cfs/__main__.py
cfs/check_md5.py
cfs/dataset.py
cfs/md5sums.txt
cfs/profusion.py
cfs/resources.py
cfs/version.py
cleveland_family_study-0.1.1.dist-info/LICENSE
cleveland_family_study-0.1.1.dist-info/METADATA
cleveland_family_study-0.1.1.dist-info/WHEEL
cleveland_family_study-0.1.1.dist-info/top_level.txt
cleveland_family_study-0.1.1.dist-info/RECORD
