Metadata-Version: 2.1
Name: cleveland-family-study
Version: 0.1.1
Summary: UNKNOWN
Home-page: UNKNOWN
License: UNKNOWN
Platform: UNKNOWN
Classifier: Programming Language :: Python :: 3
Classifier: License :: OSI Approved :: MIT License
Classifier: Operating System :: OS Independent
Requires-Python: >=3.8
Requires-Dist: xlrd (>=1.2.0)
Requires-Dist: edfpy (==0.1.0)
Requires-Dist: pandas (>=1.0.0)
Requires-Dist: terminaltables (>=3.1.0)
